nsmbl_mcp/__init__.py
nsmbl_mcp/_version.py
nsmbl_mcp/client.py
nsmbl_mcp/config.py
nsmbl_mcp/server.py
nsmbl_mcp/tools/__init__.py
nsmbl_mcp/tools/assets.py
nsmbl_mcp/tools/backtests.py
nsmbl_mcp/tools/strategies.py
nsmbl_mcp/utils/__init__.py
nsmbl_mcp/utils/errors.py
nsmbl_mcp/utils/schemas.py
nsmbl_mcp/utils/validation.py
nsmbl_mcp-0.1.dev16.dist-info/licenses/LICENSE
nsmbl_mcp-0.1.dev16.dist-info/METADATA
nsmbl_mcp-0.1.dev16.dist-info/WHEEL
nsmbl_mcp-0.1.dev16.dist-info/entry_points.txt
nsmbl_mcp-0.1.dev16.dist-info/top_level.txt
nsmbl_mcp-0.1.dev16.dist-info/RECORD
