Metadata-Version: 2.4
Name: nsmbl-mcp
Version: 0.1.dev16
Summary: MCP server for NSMBL API - enables LLMs to create systematic investment strategies and run backtests
Author-email: NSMBL <support@nsmbl.ai>
License: MIT
Project-URL: Homepage, https://github.com/nsmbl/nsmbl-mcp
Project-URL: Documentation, https://docs.nsmbl.ai
Project-URL: Repository, https://github.com/nsmbl/nsmbl-mcp
Project-URL: Issues, https://github.com/nsmbl/nsmbl-mcp/issues
Keywords: mcp,model-context-protocol,nsmbl,investment,backtest,backtesting,strategy,systematic-trading,algorithmic-trading,portfolio-management,llm,ai,claude,cursor
Classifier: Development Status :: 4 - Beta
Classifier: Intended Audience :: Developers
Classifier: Intended Audience :: Financial and Insurance Industry
Classifier: License :: OSI Approved :: MIT License
Classifier: Operating System :: OS Independent
Classifier: Programming Language :: Python :: 3
Classifier: Programming Language :: Python :: 3.10
Classifier: Programming Language :: Python :: 3.11
Classifier: Programming Language :: Python :: 3.12
Classifier: Topic :: Office/Business :: Financial :: Investment
Classifier: Topic :: Software Development :: Libraries :: Python Modules
Classifier: Typing :: Typed
Requires-Python: >=3.10
License-File: LICENSE
Requires-Dist: mcp>=0.9.0
Requires-Dist: httpx>=0.27.0
Requires-Dist: pydantic>=2.0.0
Requires-Dist: python-dotenv>=1.0.0
Provides-Extra: dev
Requires-Dist: pytest>=8.0.0; extra == "dev"
Requires-Dist: pytest-asyncio>=0.23.0; extra == "dev"
Requires-Dist: pytest-httpx>=0.30.0; extra == "dev"
Requires-Dist: black>=24.0.0; extra == "dev"
Requires-Dist: ruff>=0.3.0; extra == "dev"
Requires-Dist: mypy>=1.8.0; extra == "dev"
Dynamic: license-file
